{
  "TranslationContext": "This file contains Unit Names for the Reptilian Kingdoms Faction.",
  "Translations": [
    {
      "Key": "Reptilian Kingdoms",
      "Translation": "Reinos Saurios",
      "Comment": "Saurios = saurian/lizard. Reinos = kingdoms. Ancient lizard-men empires."
    },
    {
      "Key": "Saurian Warriors",
      "Translation": "Guerreros Saurios",
      "Comment": "Core lizard-men warriors. Guerreros = warriors, Saurios = saurian."
    },
    {
      "Key": "Crocolisk Bruisers",
      "Translation": "Golpeadores Crocólidos",
      "Comment": "Heavy reptilian warriors. Golpeadores = bruisers/strikers, Crocólidos = crocodile-like creatures."
    },
    {
      "Key": "Newt Braves",
      "Translation": "Bravos Tritones",
      "Comment": "Lesser lizard troops. Bravos = braves/warriors, Tritones = newts. Uses classical Spanish naming."
    },
    {
      "Key": "Saurian Spear",
      "Translation": "Lanzadores Saurios",
      "Comment": "Spear-wielding saurian infantry. Lanzadores = spear-throwers/lancers."
    },
    {
      "Key": "Raptor Riders",
      "Translation": "Montadores de Raptores",
      "Comment": "Fast cavalry riding velociraptors. Lightning strikes. Montadores = riders."
    },
    {
      "Key": "Pterodactyl Riders",
      "Translation": "Jinetes Pterodáctilo",
      "Comment": "Flying cavalry on pterodactyls. Air superiority. Jinetes = riders."
    },
    {
      "Key": "Newt Skirmishers",
      "Translation": "Tiradores Tritones",
      "Comment": "Light skirmishing troops. Tiradores = skirmishers/shooters."
    },
    {
      "Key": "Firelizard",
      "Translation": "Lagarto Ígneo",
      "Comment": "Fire-breathing lizard monster. Ígneo = fiery/igneous. Suggests mythical heat and power."
    },
    {
      "Key": "Triceratops",
      "Translation": "Triceratops",
      "Comment": "Kept as dinosaur name. Massive horned beast. Scientific name translates equally to Spanish."
    },
    {
      "Key": "Jungle Swarm",
      "Translation": "Enjambre de la Selva",
      "Comment": "Swarm of small reptilian creatures from the jungle. Enjambre = swarm. Fantasy wargame terminology."
    },
    {
      "Key": "Dreadmaw",
      "Translation": "Fauces del Terror",
      "Comment": "Terrifying predator. Fauces = fanged jaws/maw, Terror = dread. Evokes mythical menace."
    },
    {
      "Key": "Tyrannosaur",
      "Translation": "Tiranosaurio",
      "Comment": "King of the lizards. Tiranosaurio = Spanish form of tyrannosaur. Scientific name widely recognized."
    },
    {
      "Key": "Newt Priest",
      "Translation": "Sacerdote Tritón",
      "Comment": "Religious leader of the lesser reptilians. Sacerdote = priest. Formal, serious tone for wargame."
    },
    {
      "Key": "Saurian Warlord",
      "Translation": "Señor de la Guerra Saurio",
      "Comment": "Powerful military commander. Señor de la Guerra = warlord (literal: lord of war). Conveys authority and military might."
    },
    {
      "Key": "Ancient Toad",
      "Translation": "Sapo Ancestral",
      "Comment": "Mystical amphibian sage. Ancestral = ancient/primal. Emphasizes mystical and primordial nature."
    }
  ]
}